acace_vector_store/__init__.py
acace_vector_store-0.1.0.dist-info/METADATA
acace_vector_store-0.1.0.dist-info/WHEEL
acace_vector_store-0.1.0.dist-info/RECORD
